{"remove":{"path":"part-00000-838ac6f3-9a97-4755-9171-c61a369585be-c000.snappy.parquet","dataChange":true,"deletionTimestamp":1764005675426,"extendedFileMetadata":true,"partitionValues":{},"size":1052}}
{"add":{"path":"part-00000-a4f1a574-3628-4ff7-a472-1ef2bd44e670-c000.snappy.parquet","partitionValues":{},"size":1076,"modificationTime":1764005675432,"dataChange":true,"stats":"{\"numRecords\":5,\"minValues\":{\"id\":101,\"name\":\"Alice\",\"segment\":\"A\"},\"maxValues\":{\"segment\":\"C\",\"id\":105,\"name\":\"Eve\"},\"nullCount\":{\"id\":0,\"name\":0,\"segment\":0}}","tags":null,"baseRowId":null,"defaultRowCommitVersion":null,"clusteringProvider":null}}
{"commitInfo":{"timestamp":1764005675432,"operation":"WRITE","operationParameters":{"mode":"Overwrite"},"engineInfo":"delta-rs:py-1.2.1","operationMetrics":{"execution_time_ms":5,"num_added_files":1,"num_added_rows":5,"num_partitions":0,"num_removed_files":1},"clientVersion":"delta-rs.py-1.2.1"}}